{
"labelNombreUsuario":"Usuario",
"labelRol":"Rol",
"labelNombre":"Nombre",
"labelApellido":"Apellido",
"labelDNI":"DNI",
"labelEmail":"Email",
"ColumnaUsuario":"Usuario",
"ColumnaContraseña":"Contraseña",
"ColumnaRol":"Rol",
"ColumnaNombre":"Nombre",
"ColumnaApellido":"Apellido",
"ColumnaDNI":"DNI",
"ColumnaEmail":"Email",
"ColumnaBloqueado":"Bloqueado",
"ColumnaIntentos":"Intentos",
"buttonAltaUsuario":"Alta Usuario",
"buttonBajaUsuario":"Baja Usuario",
"buttonModificarUsuario":"Modificar Usuario",
"buttonBloquear":"Bloquear",
"buttonDesbloquear":"Desbloquear",
"buttonVolverAlMenu":"Volver al Menú",
"labelContraseña":"Contraseña",
"labelConfirmarContraseña":"Confirmar Contraseña",
"buttonCambiarContraseña":"Cambiar Contaraseña",
"buttonCerrarSesion":"Cerrar Sesión",
"labelBienvenida":"Bienvenido @{SessionManager.GestorSessionManager.sesion.NombreUsuario}",
"buttonABM":"ABM",
"buttonBitacora": "Bitácora",
"buttonAceptarCambioIdioma": "Aceptar",
"buttonCambiarIdioma": "Cambiar Idioma",
"buttonCerrarAplicacion": "Cerrar Aplicación"
}